README.rst
setup.py
./__init__.py
./getterminalsize.py
.ruamel/__init__.py
.ruamel/std/__init__.py
ruamel.std.shutil.egg-info/PKG-INFO
ruamel.std.shutil.egg-info/SOURCES.txt
ruamel.std.shutil.egg-info/dependency_links.txt
ruamel.std.shutil.egg-info/namespace_packages.txt
ruamel.std.shutil.egg-info/top_level.txt