Metadata-Version: 1.1
Name: ruamel.std.shutil
Version: 0.1.0
Summary: backports of shutil rounes (get_terminal_size)
Home-page: https://bitbucket.org/ruamel/std.shutil
Author: Anthon van der Neut
Author-email: a.van.der.neut@ruamel.eu
License: Copyright Ruamel bvba 2007-2015
Platform: UNKNOWN
Classifier: Development Status :: 4 - Beta
Classifier: Intended Audience :: Developers
Classifier: License :: Other/Proprietary License
Classifier: Operating System :: OS Independent
Classifier: Programming Language :: Python
